{
  "project_info": {
    "project_number": "912757123758",
    "project_id": "fitlife-f6b98",
    "storage_bucket": "fitlife-f6b98.firebasestorage.app"
  },
  "client": [
    {
      "client_info": {
        "mobilesdk_app_id": "1:912757123758:android:c9685ca5631476d07e1b3f",
        "android_client_info": {
          "package_name": "np.com.harishankarsah.fitlife"
        }
      },
      "oauth_client": [],
      "api_key": [
        {
          "current_key": "AIzaSyDvWaIO4zwlMNKsocKFCosbrBliK0pFR-o"
        }
      ],
      "services": {
        "appinvite_service": {
          "other_platform_oauth_client": []
        }
      }
    }
  ],
  "configuration_version": "1"
}